fig2q/__init__.py
fig2q/__main__.py
fig2q/cli.py
fig2q/downloadImage.py
fig2q/helpers.py
fig2q/infographic_config.py
fig2q/scroll_graphic_config.py
fig2q-0.1.3.dist-info/METADATA
fig2q-0.1.3.dist-info/WHEEL
fig2q-0.1.3.dist-info/entry_points.txt
fig2q-0.1.3.dist-info/top_level.txt
fig2q-0.1.3.dist-info/RECORD
