Metadata-Version: 2.4
Name: fig2q
Version: 0.1.3
Summary: Directly upload Figma designs to Q
Author-email: NZZ Visuals <visuals@nzz.ch>
Requires-Dist: requests
Requires-Dist: PyYAML
Provides-Extra: test
Requires-Dist: pytest>=7.0; extra == "test"
Requires-Dist: pytest-cov>=4.0; extra == "test"
Requires-Dist: pytest-mock>=3.10; extra == "test"
Requires-Dist: responses>=0.23; extra == "test"
